{
    "caption": "🔓 Editar Lead - Chat",
    "doc": "",
    "fields": {
        "ABD": {
            "caption": "API Key",
            "doc": "",
            "editor": "DynamicValue",
            "name": "apikey",
            "rank": 2,
            "value": "text"
        },
        "ABF": {
            "caption": "Servidor URL",
            "editor": "DynamicValue",
            "name": "url",
            "optional": true,
            "rank": 0,
            "value": "text"
        },
        "ABH": {
            "caption": "Instancia",
            "editor": "DynamicValue",
            "name": "instancia",
            "optional": true,
            "rank": 1,
            "value": "text"
        },
        "ABP": {
            "caption": "O Servidor URL e a Instancia são opcionais, caso você deixe vazio, os valores serão aqueles definidos na configuração do plugin. ⠀⠀⠀⠀⠀⠀⠀⠀⠀⠀⠀⠀⠀⠀⠀⠀⠀⠀  ⚠️⚠️ Todos os dados colocados aqui estão expostos no navegador do cliente, tenha cuidado com sua API Key e Global API Key.",
            "doc": "",
            "editor": "Label",
            "name": "apikey_doc",
            "rank": 3
        },
        "AMI": {
            "caption": "Desabilitar Fluxos",
            "default_val": 1,
            "doc": "0 = desabilitado, 1 = habilitado, DateUnix = desabilitado até essa data.  ⠀⠀⠀⠀⠀⠀⠀⠀⠀⠀⠀⠀⠀⠀⠀⠀⠀⠀⠀⠀⠀⠀⠀⠀⠀⠀⠀⠀ Como usar DateUnix: (Current date/time + hours: 10) :extract UNIX",
            "editor": "DynamicValue",
            "long_text": false,
            "name": "disableFlowsUntil",
            "options": "",
            "rank": 5,
            "value": "number"
        },
        "AMO": {
            "caption": "Campos Informativos que você pode editar e filtrar depois:",
            "doc": "Opções: all, contacts, contact_blacklist, none",
            "editor": "Label",
            "name": "info",
            "options": "",
            "rank": 6,
            "value": "text"
        },
        "AMP": {
            "caption": "Nome de exibição",
            "doc": "Primeiro nome, apelido, como preferir... Coloque um espaço em branco para apagar",
            "editor": "DynamicValue",
            "name": "nome",
            "optional": true,
            "options": "",
            "rank": 7,
            "value": "text"
        },
        "AMQ": {
            "caption": "E-mail",
            "doc": "Email... Coloque um espaço em branco para apagar",
            "editor": "DynamicValue",
            "name": "email",
            "optional": true,
            "options": "",
            "rank": 9,
            "value": "text"
        },
        "AMR": {
            "caption": "Nome Completo",
            "doc": "Nome completo... Coloque um espaço em branco para apagar",
            "editor": "DynamicValue",
            "name": "nomecompleto",
            "optional": true,
            "options": "",
            "rank": 8,
            "value": "text"
        },
        "AMS": {
            "caption": "CPF",
            "doc": "CPF... Coloque um espaço em branco para apagar",
            "editor": "DynamicValue",
            "name": "cpf",
            "optional": true,
            "options": "",
            "rank": 10,
            "value": "text"
        },
        "ANB": {
            "caption": "Status do Lead",
            "doc": "Status do Lead, exemplos: \"Assinante\"... Ou \"Prospect\", \"Lead\", \"frio\", \"quente\", faça as suas categorias e defina aqui... Coloque um espaço em branco para apagar",
            "editor": "DynamicValue",
            "name": "statusLead",
            "optional": true,
            "rank": 11,
            "value": "text"
        },
        "ANC": {
            "caption": "Notas",
            "doc": "Um texto longo sobre o Lead... Coloque um espaço em branco para apagar",
            "editor": "DynamicValue",
            "long_text": true,
            "name": "note",
            "optional": true,
            "rank": 12,
            "value": "text"
        },
        "AND": {
            "caption": "Etiquetas",
            "doc": "Exemplo: testando aplicativo | Cliente com pouco conhecimento em informática - Separadas por |, conforme exemplo, se já tiver etiquetas, para editar, você terá que passar todas as etiquetas, pois esse campo reescreve, caso queria apagar tudo, use o campo abaixo.",
            "editor": "DynamicValue",
            "name": "tags",
            "optional": true,
            "rank": 13,
            "value": "text"
        },
        "ANE": {
            "caption": "Atendimento em aberto",
            "default_val": false,
            "doc": "Atendimento em aberto ou fechado = concluído.",
            "editor": "DynamicValue",
            "name": "serviceOpen",
            "optional": true,
            "rank": 15,
            "value": "boolean"
        },
        "ANF": {
            "caption": "Atribuído à",
            "doc": "Coloque o nome ou id ao atendente que esse Lead está atribuído",
            "editor": "DynamicValue",
            "name": "assignedTo",
            "optional": true,
            "rank": 16,
            "value": "text"
        },
        "ANG": {
            "caption": "Apagar Etiquetas",
            "default_val": false,
            "doc": "Apagar todas as etiquetas",
            "editor": "DynamicValue",
            "name": "deleteTags",
            "optional": false,
            "rank": 14,
            "value": "boolean"
        },
        "ANK": {
            "caption": "Chat id - telefone",
            "doc": "Id do Chat, número de telefone",
            "editor": "DynamicValue",
            "name": "id",
            "rank": 4,
            "value": "text"
        },
        "ANL": {
            "caption": "Mensagens não lidas",
            "doc": "Coloque o número de mensagens não lidas, use para marca uma conversa como lida / não lida.",
            "editor": "DynamicValue",
            "name": "unreadcount",
            "optional": true,
            "rank": 17,
            "value": "number"
        },
        "ANX": {
            "caption": "Campos Personalizados",
            "doc": "Coloque uma lista de itens com o formato a seguir, não esqueça de colocar o \"_id\" = ao \"_id\" definido na ação de editar campos personalizado : { \"_id\": \"id do campo1\", \"value\": \"valor do campo1\" }, { \"_id\": \"id do campo2\", \"value\": \"valor do campo2\" }",
            "editor": "DynamicValue",
            "name": "customFields",
            "optional": true,
            "rank": 18,
            "value": "text"
        }
    }
}