{
    "category": "plugins",
    "display": "▶️ Enviar audio",
    "fields": {
        "AGc": {
            "caption": "Servidor URL",
            "editor": "DynamicValue",
            "name": "url",
            "optional": true,
            "rank": 0,
            "value": "text"
        },
        "AGd": {
            "caption": "API Key",
            "editor": "DynamicValue",
            "name": "apikey",
            "optional": true,
            "rank": 3,
            "value": "text"
        },
        "AGi": {
            "caption": "Instancia",
            "editor": "DynamicValue",
	    "optional": true,
            "name": "instancia",
            "rank": 2,
            "value": "text"
        },
        "AGm": {
            "caption": "",
            "editor": "Label",
            "name": "url_opcional",
            "rank": 1
        },
        "AGn": {
            "caption": "O Servidor URL, a API Key e a Instancia são opcionais, caso você deixe vazio, os valores serão aqueles definidos na configuração do plugin.",
            "editor": "Label",
            "name": "apikey_opcional",
            "rank": 3
        },
        "AHw": {
            "caption": "Destinatário",
            "editor": "DynamicValue",
            "name": "number",
            "rank": 5,
            "value": "text"
        },
        "AHx": {
            "caption": "URL do audio",
            "editor": "DynamicValue",
            "name": "audio",
            "rank": 6,
            "value": "text"
        },
        "AHy": {
            "caption": "delay",
            "default_val": 0,
            "editor": "DynamicValue",
            "name": "delay",
            "rank": 7,
            "value": "number"
        }
    },
    "return_value": {
        "AGf": {
            "caption": "log",
            "name": "log",
            "rank": 0,
            "value": "text"
        },
        "AGj": {
            "caption": "remoteJid",
            "is_list": false,
            "name": "remoteJid",
            "rank": 3,
            "value": "text"
        },
        "AGk": {
            "caption": "error",
            "name": "error",
            "rank": 1,
            "value": "boolean"
        },
        "AGl": {
            "caption": "error_log",
            "name": "error_log",
            "rank": 2,
            "value": "text"
        },
        "AHz": {
            "caption": "fromMe",
            "name": "fromMe",
            "rank": 4,
            "value": "boolean"
        },
        "AIA": {
            "caption": "id",
            "name": "id",
            "rank": 5,
            "value": "text"
        },
        "AIB": {
            "caption": "status",
            "name": "status",
            "rank": 6,
            "value": "text"
        }
    },
    "type": "server_side"
}